packagevikrant/__init__.py
packagevikrant/init.py
packagevikrant-1.4.dist-info/METADATA
packagevikrant-1.4.dist-info/WHEEL
packagevikrant-1.4.dist-info/license
packagevikrant-1.4.dist-info/top_level.txt
packagevikrant-1.4.dist-info/RECORD
