Metadata-Version: 2.1
Name: packagevikrant
Version: 1.4
Summary: This code is written by Vikrant Singh.
Home-page: UNKNOWN
Author: Vikrant Singh
License: MIT
Platform: UNKNOWN
Requires-Dist: pyttsx3
